setup.py
distributions/Binomialdistribution.py
distributions/Gaussiandistribution.py
distributions/Generaldistribution.py
distributions/__init__.py
raj_distributions.egg-info/PKG-INFO
raj_distributions.egg-info/SOURCES.txt
raj_distributions.egg-info/dependency_links.txt
raj_distributions.egg-info/not-zip-safe
raj_distributions.egg-info/top_level.txt